hugon/__init__.py
hugon/hugon.py
hugon-0.1.7.dist-info/AUTHORS.rst
hugon-0.1.7.dist-info/LICENSE
hugon-0.1.7.dist-info/METADATA
hugon-0.1.7.dist-info/WHEEL
hugon-0.1.7.dist-info/entry_points.txt
hugon-0.1.7.dist-info/top_level.txt
hugon-0.1.7.dist-info/RECORD
