Metadata-Version: 2.1
Name: hugon
Version: 0.1.7
Summary: An incredibly simple python script that makes working with archtypes in Hugo 0.5x much easier.
Home-page: https://github.com/hithismani/hugon
Author: Mani Kumar
Author-email: hi@manikumar.in
License: MIT license
Keywords: hugon
Platform: UNKNOWN
Classifier: Development Status :: 2 - Pre-Alpha
Classifier: Intended Audience :: Developers
Classifier: License :: OSI Approved :: MIT License
Classifier: Natural Language :: English
Classifier: Programming Language :: Python :: 3
Classifier: Programming Language :: Python :: 3.5
Classifier: Programming Language :: Python :: 3.6
Classifier: Programming Language :: Python :: 3.7
Classifier: Programming Language :: Python :: 3.8
Requires-Python: >=3.5
